{
  "0.571321370198524": {
    "money_100": [
      {
        "phone": 994705975997,
        "operation_id": "4561176e-c379-4bcb-bdaf-04ff04f14e94"
      },
      {
        "phone": 994507076017,
        "operation_id": "659ccf27-1407-4c54-976f-9dfc00fd7ddd"
      },
      {
        "phone": 994507169462,
        "operation_id": "b14eb1c7-d336-408f-8592-a8a1b2094384"
      }
    ]
  },
  "0.6759155742319396": {
    "money_100": [
      {
        "phone": 994502038816,
        "operation_id": "6454be20-f09e-4268-8fcb-a831f011b9c9"
      }
    ]
  }
}